{
  "ShowDamage": true,
  "ShowDropZones": true,
  "AlternateCameraBehaviour": false,
  "ShowChat": true,
  "SoundVolumeRange": 0.5,
  "BackgroundSound": true,
  "GameSound": true,
  "ShowSkybox": true,
  "EnableShadow": true,
  "DeepShadows": true,
  "GlobalIllumination": true,
  "MapIllumination": true,
  "WeaponIllumination": true,
  "LightShadows": false,
  "Antialiasing": true,
  "ShowFPSPing": true,
  "SoftParticles": true,
  "AutomaticGraphicsQuality": true,
  "Grass": true,
  "Dust": true,
  "SSAO": true,
  "Fog": true,
  "TankTraces": true,
  "ShowWeather": true
}